main.py
cli/__init__.py
cli/config.py
cli/db.py
cli/query.py
core/__init__.py
core/db.py
core/introspect.py
core/llm.py
core/query.py
tesh_query-0.3.1.dist-info/licenses/LICENSE
utils/__init__.py
utils/formater.py
utils/keys.py
tesh_query-0.3.1.dist-info/METADATA
tesh_query-0.3.1.dist-info/WHEEL
tesh_query-0.3.1.dist-info/entry_points.txt
tesh_query-0.3.1.dist-info/top_level.txt
tesh_query-0.3.1.dist-info/RECORD
