Metadata-Version: 2.4
Name: tesh-query
Version: 0.3.1
Summary: A CLI tool that converts natural language queries into SQL and returns relevant tables using natural language.
Author-email: Shashank <shashankgundas1@gmail.com>
License: MIT
Project-URL: Homepage, https://github.com/theshashank1/TESH-Query
Project-URL: Bug Tracker, https://github.com/theshashank1/TESH-Query/issues
Keywords: sql,cli,database,natural language,AI,LLM
Classifier: Programming Language :: Python :: 3
Classifier: Programming Language :: Python :: 3.9
Classifier: Programming Language :: Python :: 3.10
Classifier: Programming Language :: Python :: 3.11
Classifier: Programming Language :: Python :: 3.12
Classifier: Operating System :: OS Independent
Requires-Python: >=3.9
License-File: LICENSE
Requires-Dist: SQLAlchemy~=2.0.41
Requires-Dist: python-dotenv~=1.1.0
Requires-Dist: psycopg2-binary~=2.9.10
Requires-Dist: langchain~=0.3.25
Requires-Dist: langchain-core~=0.3.61
Requires-Dist: langchain-google-genai~=2.1.4
Requires-Dist: typer[all]~=0.15.4
Requires-Dist: rich~=14.0.0
Requires-Dist: logfire~=3.16.0
Requires-Dist: tabulate~=0.9.0
Provides-Extra: dev
Requires-Dist: pytest~=8.3.5; extra == "dev"
Requires-Dist: autopep8~=2.3.2; extra == "dev"
Requires-Dist: pre-commit~=4.2.0; extra == "dev"
Requires-Dist: flake8~=6.1.0; extra == "dev"
Requires-Dist: isort~=5.13.2; extra == "dev"
Dynamic: license-file
